wombat/multiprocessing/__init__.py
wombat/multiprocessing/errors.py
wombat/multiprocessing/logging.py
wombat/multiprocessing/orchestrator.py
wombat/multiprocessing/progress.py
wombat/multiprocessing/systems.py
wombat/multiprocessing/worker.py
wombat/multiprocessing/ipc/buffer.py
wombat/multiprocessing/ipc/shared_memory_hash_map.py
wombat/multiprocessing/ipc/utilities.py
wombat/multiprocessing/ipc/queues/smqueue.py
wombat/multiprocessing/ipc/queues/trait_queue.py
wombat/multiprocessing/ipc/queues/utilities.py
wombat/multiprocessing/traits/__init__.py
wombat/multiprocessing/traits/accounting.py
wombat/multiprocessing/traits/breaker.py
wombat/multiprocessing/traits/consumes.py
wombat/multiprocessing/traits/debounce.py
wombat/multiprocessing/traits/decorators.py
wombat/multiprocessing/traits/decorators.pyi
wombat/multiprocessing/traits/delayed.py
wombat/multiprocessing/traits/evaluatable.py
wombat/multiprocessing/traits/expirable.py
wombat/multiprocessing/traits/lifecycle.py
wombat/multiprocessing/traits/loggable.py
wombat/multiprocessing/traits/models.py
wombat/multiprocessing/traits/pinned.py
wombat/multiprocessing/traits/produces.py
wombat/multiprocessing/traits/progress.py
wombat/multiprocessing/traits/rate_limit.py
wombat/multiprocessing/traits/requires_props.py
wombat/multiprocessing/traits/retryable.py
wombat/multiprocessing/traits/state.py
wombat/multiprocessing/traits/tagged.py
wombat/multiprocessing/traits/timeout.py
qpool-0.5.14.dist-info/METADATA
qpool-0.5.14.dist-info/WHEEL
qpool-0.5.14.dist-info/RECORD
