Metadata-Version: 2.4
Name: qpool
Version: 0.5.14
Summary: Trait based multiprocessing with queues
Requires-Python: >=3.11.11
Requires-Dist: aiohttp>=3.11.11
Requires-Dist: atomics>=1.0.3
Requires-Dist: certifi>=2025.1.31
Requires-Dist: line-profiler>=5.0.0
Requires-Dist: matplotlib>=3.10.5
Requires-Dist: msgpack>=1.1.1
Requires-Dist: pydantic-partial>=0.6.0
Requires-Dist: pydantic>=2.9.1
Requires-Dist: python-dotenv>=1.0.1
Requires-Dist: rich<14.0,>=13.0
Requires-Dist: uvloop>=0.21.0
Requires-Dist: wombat-utils>=0.2.4
